couchdbrq/__init__.py
couchdbrq/client.py
couchdbrq/pinger.py
couchdbrq/view.py
couchdbrq/tests/__init__.py
couchdbrq/tests/client.py
couchdb_python_requests-0.4.2.dist-info/METADATA
couchdb_python_requests-0.4.2.dist-info/WHEEL
couchdb_python_requests-0.4.2.dist-info/entry_points.txt
couchdb_python_requests-0.4.2.dist-info/top_level.txt
couchdb_python_requests-0.4.2.dist-info/RECORD
