Metadata-Version: 2.1
Name: couchdb-python-requests
Version: 0.4.2
Summary: CouchDB's Python wrapper (using requests library)
Home-page: https://bitbucket.org/angry_elf/couchdb-python-requests
Author: Alexey Elfman
Author-email: elf2001@gmail.com
License: GPL
Classifier: Development Status :: 2 - Pre-Alpha
Classifier: Intended Audience :: Developers
Classifier: License :: OSI Approved :: GNU General Public License (GPL)
Classifier: Natural Language :: English
Classifier: Programming Language :: Python
Classifier: Topic :: Software Development :: Libraries :: Python Modules
Classifier: Topic :: Database :: Front-Ends
Requires-Dist: requests
